yallm/__init__.py
yallm-0.0.0.dist-info/WHEEL
yallm-0.0.0.dist-info/entry_points.txt
yallm-0.0.0.dist-info/METADATA
yallm-0.0.0.dist-info/RECORD
