Metadata-Version: 2.3
Name: yallm
Version: 0.0.0
Summary: yet another LLM
Author: Tang Ziya
Author-email: Tang Ziya <tcztzy@gmail.Com>
Requires-Python: >=3.14
